hal/__init__.py
hal/classify.py
hal/custom_server.py
hal/graph.py
hal/metric.py
hal/pipeline.py
hal/plotjs.py
hal/plotlygraph.py
hal/plotting.py
hal/purify.py
hal/test.py
hal/tree.py
hal/tupledict.py
hal/utility.py
hal/js/haltree.js
hal_x-0.993.dist-info/LICENSE
hal_x-0.993.dist-info/METADATA
hal_x-0.993.dist-info/WHEEL
hal_x-0.993.dist-info/top_level.txt
hal_x-0.993.dist-info/RECORD
