Metadata-Version: 2.1
Name: hal-x
Version: 0.993
Summary: Clustering via hierarchical agglomerative learning
Home-page: https://alexandreday.github.io/
Author: Alexandre Day
Author-email: alexandre.day1@gmail.com
License: MIT
Platform: UNKNOWN
Classifier: Programming Language :: Python :: 3.8
Classifier: License :: OSI Approved :: MIT License
Classifier: Operating System :: OS Independent
License-File: LICENSE
Requires-Dist: fitsne (>=0.2.5)
Requires-Dist: scikit-learn (>=0.19)
Requires-Dist: fdc (>=1.15)
